{"priority": "minor", "kind": "proposal", "repository": {"links": {"self": {"href": "data/repositories/osrf/handsim.json"}, "html": {"href": "#!/osrf/handsim"}, "avatar": {"href": "data/bytebucket.org/ravatar/{9c7d89af-6eb6-40b1-9f69-da1ae9d129ce}ts=c_plus_plus"}}, "type": "repository", "name": "handsim", "full_name": "osrf/handsim", "uuid": "{9c7d89af-6eb6-40b1-9f69-da1ae9d129ce}"}, "links": {"attachments": {"href": "data/repositories/osrf/handsim/issues/82/attachments_page=1.json"}, "self": {"href": "data/repositories/osrf/handsim/issues/82.json"}, "watch": {"href": "https://api.bitbucket.org/2.0/repositories/osrf/handsim/issues/82/watch"}, "comments": {"href": "data/repositories/osrf/handsim/issues/82/comments_page=1.json"}, "html": {"href": "#!/osrf/handsim/issues/82/give-haptix-users-ability-to-write-their"}, "vote": {"href": "https://api.bitbucket.org/2.0/repositories/osrf/handsim/issues/82/vote"}}, "reporter": {"display_name": "David Kluger", "uuid": "{0f991d57-5bb5-4dc7-bee0-56547fac3a17}", "links": {"self": {"href": "https://api.bitbucket.org/2.0/users/%7B0f991d57-5bb5-4dc7-bee0-56547fac3a17%7D"}, "html": {"href": "https://bitbucket.org/%7B0f991d57-5bb5-4dc7-bee0-56547fac3a17%7D/"}, "avatar": {"href": "https://bitbucket.org/account/DKluger/avatar/"}}, "nickname": "DKluger", "type": "user", "account_id": null}, "title": "Give HAPTIX users ability to write their own API functions", "component": null, "votes": 0, "watches": 4, "content": {"raw": "This might already be doable, but we'd like the ability to write our own API functions to interact with the VRE (starting with C/C++ code, and then create MATLAB .mex wrappers). This would allow us to write simulation-specific functions to help use the VRE for experiments.\r\n\r\nIs this doable with the VRE and SDK in their current state? If yes, could a tutorial be written explaining how to do this? If not, could this feature be added to a future release?", "markup": "markdown", "html": "<p>This might already be doable, but we'd like the ability to write our own API functions to interact with the VRE (starting with C/C++ code, and then create MATLAB .mex wrappers). This would allow us to write simulation-specific functions to help use the VRE for experiments.</p>\n<p>Is this doable with the VRE and SDK in their current state? If yes, could a tutorial be written explaining how to do this? If not, could this feature be added to a future release?</p>", "type": "rendered"}, "assignee": null, "state": "resolved", "version": null, "edited_on": null, "created_on": "2015-04-21T20:41:11.506741+00:00", "milestone": {"name": "Release Pending", "links": {"self": {"href": "data/repositories/osrf/handsim/milestones/161324.json"}}}, "updated_on": "2015-05-18T17:52:38.307712+00:00", "type": "issue", "id": 82}