{"links": {"self": {"href": "data/repositories/osrf/haptix_api/pullrequests/4/comments/6031904.json"}, "html": {"href": "#!/osrf/haptix_api/pull-requests/4/_/diff#comment-6031904"}}, "parent": {"id": 5974399, "links": {"self": {"href": "data/repositories/osrf/haptix_api/pullrequests/4/comments/5974399.json"}, "html": {"href": "#!/osrf/haptix_api/pull-requests/4/_/diff#comment-5974399"}}}, "deleted": false, "pullrequest": {"type": "pullrequest", "id": 4, "links": {"self": {"href": "data/repositories/osrf/haptix_api/pullrequests/4.json"}, "html": {"href": "#!/osrf/haptix_api/pull-requests/4"}}, "title": "Update to the simulation API"}, "content": {"raw": "Side question, is MuJoCo XML similar to [URDF](http://wiki.ros.org/urdf/XML/model) / [SDF](http://www.sdformat.org/)? IMHO these are all human readable and editable formats (as compared to Collada, which requires a graphical model editor).\n\n", "markup": "markdown", "html": "<p>Side question, is MuJoCo XML similar to <a data-is-external-link=\"true\" href=\"http://wiki.ros.org/urdf/XML/model\" rel=\"nofollow\">URDF</a> / <a data-is-external-link=\"true\" href=\"http://www.sdformat.org/\" rel=\"nofollow\">SDF</a>? IMHO these are all human readable and editable formats (as compared to Collada, which requires a graphical model editor).</p>", "type": "rendered"}, "created_on": "2015-04-02T07:51:35.466209+00:00", "user": {"display_name": "John Hsu", "uuid": "{0a186eae-abf0-4514-a951-23db5eccc286}", "links": {"self": {"href": "https://api.bitbucket.org/2.0/users/%7B0a186eae-abf0-4514-a951-23db5eccc286%7D"}, "html": {"href": "https://bitbucket.org/%7B0a186eae-abf0-4514-a951-23db5eccc286%7D/"}, "avatar": {"href": "https://avatar-management--avatars.us-west-2.prod.public.atl-paas.net/557058:f3968cd3-4910-4384-8349-482a6c7889ec/5445ce6e-6273-47f0-84eb-621c86ca11cb/128"}}, "nickname": "hsu", "type": "user", "account_id": "557058:f3968cd3-4910-4384-8349-482a6c7889ec"}, "updated_on": "2015-04-02T07:51:35.473885+00:00", "type": "pullrequest_comment", "id": 6031904}