{"pagelen": 100, "values": [{"links": {"self": {"href": "data/repositories/osrf/handsim/pullrequests/128/comments/7168181.json"}, "html": {"href": "#!/osrf/handsim/pull-requests/128/_/diff#comment-7168181"}}, "deleted": false, "pullrequest": {"type": "pullrequest", "id": 128, "links": {"self": {"href": "data/repositories/osrf/handsim/pullrequests/128.json"}, "html": {"href": "#!/osrf/handsim/pull-requests/128"}}, "title": "DRC Finals Demo: change force limits for Hanoi world"}, "content": {"raw": "Should we merge this one first and then add the 3rd task?", "markup": "markdown", "html": "<p>Should we merge this one first and then add the 3rd task?</p>", "type": "rendered"}, "created_on": "2015-05-28T22:02:56.885518+00:00", "user": {"display_name": "Louise Poubel", "uuid": "{5cfa2075-477b-4ded-bdb9-8d2479544ec4}", "links": {"self": {"href": "https://api.bitbucket.org/2.0/users/%7B5cfa2075-477b-4ded-bdb9-8d2479544ec4%7D"}, "html": {"href": "https://bitbucket.org/%7B5cfa2075-477b-4ded-bdb9-8d2479544ec4%7D/"}, "avatar": {"href": "https://avatar-management--avatars.us-west-2.prod.public.atl-paas.net/557058:6ff86fcb-b7ab-44a5-b8a6-f6d9cae8b6e8/7d903d90-c5ea-4182-b7ef-0d467e9e1c74/128"}}, "nickname": "chapulina", "type": "user", "account_id": "557058:6ff86fcb-b7ab-44a5-b8a6-f6d9cae8b6e8"}, "updated_on": "2015-05-28T22:02:56.897792+00:00", "type": "pullrequest_comment", "id": 7168181}, {"links": {"self": {"href": "data/repositories/osrf/handsim/pullrequests/128/comments/7190924.json"}, "html": {"href": "#!/osrf/handsim/pull-requests/128/_/diff#comment-7190924"}}, "parent": {"id": 7168181, "links": {"self": {"href": "data/repositories/osrf/handsim/pullrequests/128/comments/7168181.json"}, "html": {"href": "#!/osrf/handsim/pull-requests/128/_/diff#comment-7168181"}}, "depth": 1}, "deleted": false, "pullrequest": {"type": "pullrequest", "id": 128, "links": {"self": {"href": "data/repositories/osrf/handsim/pullrequests/128.json"}, "html": {"href": "#!/osrf/handsim/pull-requests/128"}}, "title": "DRC Finals Demo: change force limits for Hanoi world"}, "content": {"raw": "yeah, it will make testing the tetris blocks easier", "markup": "markdown", "html": "<p>yeah, it will make testing the tetris blocks easier</p>", "type": "rendered"}, "created_on": "2015-05-29T18:31:14.846025+00:00", "user": {"display_name": "Jackie K", "uuid": "{e3d60b62-b7c7-4863-b9b9-cdae9f123cec}", "links": {"self": {"href": "https://api.bitbucket.org/2.0/users/%7Be3d60b62-b7c7-4863-b9b9-cdae9f123cec%7D"}, "html": {"href": "https://bitbucket.org/%7Be3d60b62-b7c7-4863-b9b9-cdae9f123cec%7D/"}, "avatar": {"href": "data/secure.gravatar.com/avatar/ea011fa2919d4bd4568b32b440eda779d=httpsavatar-management--avatars.us-west-2.prod.public.atl-paas.netinitialsJK-0.png"}}, "nickname": "jacquelinekay", "type": "user", "account_id": "557058:f56c822f-f75c-4665-80f9-6e7764893b9c"}, "updated_on": "2015-05-29T18:31:14.852470+00:00", "type": "pullrequest_comment", "id": 7190924}, {"links": {"self": {"href": "data/repositories/osrf/handsim/pullrequests/128/comments/7190930.json"}, "html": {"href": "#!/osrf/handsim/pull-requests/128/_/diff#comment-7190930"}}, "parent": {"id": 7190924, "links": {"self": {"href": "data/repositories/osrf/handsim/pullrequests/128/comments/7190924.json"}, "html": {"href": "#!/osrf/handsim/pull-requests/128/_/diff#comment-7190924"}}, "depth": 2}, "deleted": false, "pullrequest": {"type": "pullrequest", "id": 128, "links": {"self": {"href": "data/repositories/osrf/handsim/pullrequests/128.json"}, "html": {"href": "#!/osrf/handsim/pull-requests/128"}}, "title": "DRC Finals Demo: change force limits for Hanoi world"}, "content": {"raw": "Merge it when you approve :)", "markup": "markdown", "html": "<p>Merge it when you approve :)</p>", "type": "rendered"}, "created_on": "2015-05-29T18:31:27.198789+00:00", "user": {"display_name": "Jackie K", "uuid": "{e3d60b62-b7c7-4863-b9b9-cdae9f123cec}", "links": {"self": {"href": "https://api.bitbucket.org/2.0/users/%7Be3d60b62-b7c7-4863-b9b9-cdae9f123cec%7D"}, "html": {"href": "https://bitbucket.org/%7Be3d60b62-b7c7-4863-b9b9-cdae9f123cec%7D/"}, "avatar": {"href": "data/secure.gravatar.com/avatar/ea011fa2919d4bd4568b32b440eda779d=httpsavatar-management--avatars.us-west-2.prod.public.atl-paas.netinitialsJK-0.png"}}, "nickname": "jacquelinekay", "type": "user", "account_id": "557058:f56c822f-f75c-4665-80f9-6e7764893b9c"}, "updated_on": "2015-05-29T18:31:27.206444+00:00", "type": "pullrequest_comment", "id": 7190930}], "page": 1, "size": 3}