{"links": {"self": {"href": "data/repositories/osrf/haptix-comm/pullrequests/75/comments/7227390.json"}, "code": {"href": "https://api.bitbucket.org/2.0/repositories/osrf/haptix-comm/diff/osrf/haptix-comm:d38cb8472161..7b947674eb9a?path=test%2Fintegration%2FtwoProcessesSimAPI.cc"}, "html": {"href": "#!/osrf/haptix-comm/pull-requests/75/_/diff#comment-7227390"}}, "deleted": false, "pullrequest": {"type": "pullrequest", "id": 75, "links": {"self": {"href": "data/repositories/osrf/haptix-comm/pullrequests/75.json"}, "html": {"href": "#!/osrf/haptix-comm/pull-requests/75"}}, "title": "Test the simulation API using separate processes"}, "content": {"raw": "Nice, maybe I should use this in the `handsim` tests", "markup": "markdown", "html": "<p>Nice, maybe I should use this in the <code>handsim</code> tests</p>", "type": "rendered"}, "created_on": "2015-06-01T22:09:53.850117+00:00", "user": {"display_name": "Jackie K", "uuid": "{e3d60b62-b7c7-4863-b9b9-cdae9f123cec}", "links": {"self": {"href": "https://api.bitbucket.org/2.0/users/%7Be3d60b62-b7c7-4863-b9b9-cdae9f123cec%7D"}, "html": {"href": "https://bitbucket.org/%7Be3d60b62-b7c7-4863-b9b9-cdae9f123cec%7D/"}, "avatar": {"href": "data/secure.gravatar.com/avatar/ea011fa2919d4bd4568b32b440eda779d=httpsavatar-management--avatars.us-west-2.prod.public.atl-paas.netinitialsJK-0.png"}}, "nickname": "jacquelinekay", "type": "user", "account_id": "557058:f56c822f-f75c-4665-80f9-6e7764893b9c"}, "inline": {"to": 157, "from": null, "outdated": false, "path": "test/integration/twoProcessesSimAPI.cc"}, "updated_on": "2015-06-01T22:09:53.855562+00:00", "type": "pullrequest_comment", "id": 7227390}