{"pagelen": 50, "values": [{"update": {"description": "The tactors were failing to activate because they look for device `/dev/ttyACM0` by default, but sometimes the USB devices shows up as `/dev/ttyACM1`. This pull request does a device sweep and returns with an error if none of the possible devices were found.", "title": "DRC Finals Demo: check a range of USB devices for tactors", "destination": {"commit": {"hash": "c45d34ebbbd8", "type": "commit", "links": {"self": {"href": "data/repositories/osrf/handsim/commit/c45d34ebbbd8.json"}, "html": {"href": "#!/osrf/handsim/commits/c45d34ebbbd8"}}}, "repository": {"links": {"self": {"href": "data/repositories/osrf/handsim.json"}, "html": {"href": "#!/osrf/handsim"}, "avatar": {"href": "data/bytebucket.org/ravatar/{9c7d89af-6eb6-40b1-9f69-da1ae9d129ce}ts=c_plus_plus"}}, "type": "repository", "name": "handsim", "full_name": "osrf/handsim", "uuid": "{9c7d89af-6eb6-40b1-9f69-da1ae9d129ce}"}, "branch": {"name": "game_demos"}}, "reason": "i'm looking into redoing the Arduino code so it's less overwhelming. declining this for now", "source": {"commit": {"hash": "5d1f0ca4e1e7", "type": "commit", "links": {"self": {"href": "data/repositories/osrf/handsim/commit/5d1f0ca4e1e7.json"}, "html": {"href": "#!/osrf/handsim/commits/5d1f0ca4e1e7"}}}, "repository": {"links": {"self": {"href": "data/repositories/osrf/handsim.json"}, "html": {"href": "#!/osrf/handsim"}, "avatar": {"href": "data/bytebucket.org/ravatar/{9c7d89af-6eb6-40b1-9f69-da1ae9d129ce}ts=c_plus_plus"}}, "type": "repository", "name": "handsim", "full_name": "osrf/handsim", "uuid": "{9c7d89af-6eb6-40b1-9f69-da1ae9d129ce}"}, "branch": {"name": "game_demos_tactors"}}, "state": "DECLINED", "author": {"display_name": "Jackie K", "uuid": "{e3d60b62-b7c7-4863-b9b9-cdae9f123cec}", "links": {"self": {"href": "https://api.bitbucket.org/2.0/users/%7Be3d60b62-b7c7-4863-b9b9-cdae9f123cec%7D"}, "html": {"href": "https://bitbucket.org/%7Be3d60b62-b7c7-4863-b9b9-cdae9f123cec%7D/"}, "avatar": {"href": "data/secure.gravatar.com/avatar/ea011fa2919d4bd4568b32b440eda779d=httpsavatar-management--avatars.us-west-2.prod.public.atl-paas.netinitialsJK-0.png"}}, "nickname": "jacquelinekay", "type": "user", "account_id": "557058:f56c822f-f75c-4665-80f9-6e7764893b9c"}, "date": "2015-05-20T01:04:25.857580+00:00"}, "pull_request": {"type": "pullrequest", "id": 121, "links": {"self": {"href": "data/repositories/osrf/handsim/pullrequests/121.json"}, "html": {"href": "#!/osrf/handsim/pull-requests/121"}}, "title": "DRC Finals Demo: check a range of USB devices for tactors"}}, {"comment": {"links": {"self": {"href": "data/repositories/osrf/handsim/pullrequests/121/comments/6971071.json"}, "html": {"href": "#!/osrf/handsim/pull-requests/121/_/diff#comment-6971071"}}, "deleted": false, "pullrequest": {"type": "pullrequest", "id": 121, "links": {"self": {"href": "data/repositories/osrf/handsim/pullrequests/121.json"}, "html": {"href": "#!/osrf/handsim/pull-requests/121"}}, "title": "DRC Finals Demo: check a range of USB devices for tactors"}, "content": {"raw": "conflicts", "markup": "markdown", "html": "<p>conflicts</p>", "type": "rendered"}, "created_on": "2015-05-20T01:02:29.748639+00:00", "user": {"display_name": "Steve Peters", "uuid": "{2ccfed09-18b8-4921-8d58-15ef01092802}", "links": {"self": {"href": "https://api.bitbucket.org/2.0/users/%7B2ccfed09-18b8-4921-8d58-15ef01092802%7D"}, "html": {"href": "https://bitbucket.org/%7B2ccfed09-18b8-4921-8d58-15ef01092802%7D/"}, "avatar": {"href": "data/secure.gravatar.com/avatar/1fb4816dad9e68337d3096f750951f6cd=httpsavatar-management--avatars.us-west-2.prod.public.atl-paas.netinitialsSP-1.png"}}, "nickname": "Steven Peters", "type": "user", "account_id": "557058:5de38267-b118-494c-aa76-4fab35448816"}, "updated_on": "2015-05-20T01:02:29.757975+00:00", "type": "pullrequest_comment", "id": 6971071}, "pull_request": {"type": "pullrequest", "id": 121, "links": {"self": {"href": "data/repositories/osrf/handsim/pullrequests/121.json"}, "html": {"href": "#!/osrf/handsim/pull-requests/121"}}, "title": "DRC Finals Demo: check a range of USB devices for tactors"}}, {"update": {"description": "The tactors were failing to activate because they look for device `/dev/ttyACM0` by default, but sometimes the USB devices shows up as `/dev/ttyACM1`. This pull request does a device sweep and returns with an error if none of the possible devices were found.", "title": "DRC Finals Demo: check a range of USB devices for tactors", "destination": {"commit": {"hash": "c45d34ebbbd8", "type": "commit", "links": {"self": {"href": "data/repositories/osrf/handsim/commit/c45d34ebbbd8.json"}, "html": {"href": "#!/osrf/handsim/commits/c45d34ebbbd8"}}}, "repository": {"links": {"self": {"href": "data/repositories/osrf/handsim.json"}, "html": {"href": "#!/osrf/handsim"}, "avatar": {"href": "data/bytebucket.org/ravatar/{9c7d89af-6eb6-40b1-9f69-da1ae9d129ce}ts=c_plus_plus"}}, "type": "repository", "name": "handsim", "full_name": "osrf/handsim", "uuid": "{9c7d89af-6eb6-40b1-9f69-da1ae9d129ce}"}, "branch": {"name": "game_demos"}}, "reason": "", "source": {"commit": {"hash": "5d1f0ca4e1e7", "type": "commit", "links": {"self": {"href": "data/repositories/osrf/handsim/commit/5d1f0ca4e1e7.json"}, "html": {"href": "#!/osrf/handsim/commits/5d1f0ca4e1e7"}}}, "repository": {"links": {"self": {"href": "data/repositories/osrf/handsim.json"}, "html": {"href": "#!/osrf/handsim"}, "avatar": {"href": "data/bytebucket.org/ravatar/{9c7d89af-6eb6-40b1-9f69-da1ae9d129ce}ts=c_plus_plus"}}, "type": "repository", "name": "handsim", "full_name": "osrf/handsim", "uuid": "{9c7d89af-6eb6-40b1-9f69-da1ae9d129ce}"}, "branch": {"name": "game_demos_tactors"}}, "state": "OPEN", "author": {"display_name": "Jackie K", "uuid": "{e3d60b62-b7c7-4863-b9b9-cdae9f123cec}", "links": {"self": {"href": "https://api.bitbucket.org/2.0/users/%7Be3d60b62-b7c7-4863-b9b9-cdae9f123cec%7D"}, "html": {"href": "https://bitbucket.org/%7Be3d60b62-b7c7-4863-b9b9-cdae9f123cec%7D/"}, "avatar": {"href": "data/secure.gravatar.com/avatar/ea011fa2919d4bd4568b32b440eda779d=httpsavatar-management--avatars.us-west-2.prod.public.atl-paas.netinitialsJK-0.png"}}, "nickname": "jacquelinekay", "type": "user", "account_id": "557058:f56c822f-f75c-4665-80f9-6e7764893b9c"}, "date": "2015-05-20T00:20:58.426305+00:00"}, "pull_request": {"type": "pullrequest", "id": 121, "links": {"self": {"href": "data/repositories/osrf/handsim/pullrequests/121.json"}, "html": {"href": "#!/osrf/handsim/pull-requests/121"}}, "title": "DRC Finals Demo: check a range of USB devices for tactors"}}, {"update": {"description": "The tactors were failing to activate because they look for device `/dev/ttyACM0` by default, but sometimes the USB devices shows up as `/dev/ttyACM1`. This pull request does a device sweep and returns with an error if none of the possible devices were found.", "title": "DRC Finals Demo: check a range of USB devices for tactors", "destination": {"commit": {"hash": "57edad95d0a7", "type": "commit", "links": {"self": {"href": "data/repositories/osrf/handsim/commit/57edad95d0a7.json"}, "html": {"href": "#!/osrf/handsim/commits/57edad95d0a7"}}}, "repository": {"links": {"self": {"href": "data/repositories/osrf/handsim.json"}, "html": {"href": "#!/osrf/handsim"}, "avatar": {"href": "data/bytebucket.org/ravatar/{9c7d89af-6eb6-40b1-9f69-da1ae9d129ce}ts=c_plus_plus"}}, "type": "repository", "name": "handsim", "full_name": "osrf/handsim", "uuid": "{9c7d89af-6eb6-40b1-9f69-da1ae9d129ce}"}, "branch": {"name": "game_demos"}}, "reason": "", "source": {"commit": {"hash": "defd6ea4154c", "type": "commit", "links": {"self": {"href": "data/repositories/osrf/handsim/commit/defd6ea4154c.json"}, "html": {"href": "#!/osrf/handsim/commits/defd6ea4154c"}}}, "repository": {"links": {"self": {"href": "data/repositories/osrf/handsim.json"}, "html": {"href": "#!/osrf/handsim"}, "avatar": {"href": "data/bytebucket.org/ravatar/{9c7d89af-6eb6-40b1-9f69-da1ae9d129ce}ts=c_plus_plus"}}, "type": "repository", "name": "handsim", "full_name": "osrf/handsim", "uuid": "{9c7d89af-6eb6-40b1-9f69-da1ae9d129ce}"}, "branch": {"name": "game_demos_tactors"}}, "state": "OPEN", "author": {"display_name": "John Hsu", "uuid": "{0a186eae-abf0-4514-a951-23db5eccc286}", "links": {"self": {"href": "https://api.bitbucket.org/2.0/users/%7B0a186eae-abf0-4514-a951-23db5eccc286%7D"}, "html": {"href": "https://bitbucket.org/%7B0a186eae-abf0-4514-a951-23db5eccc286%7D/"}, "avatar": {"href": "https://avatar-management--avatars.us-west-2.prod.public.atl-paas.net/557058:f3968cd3-4910-4384-8349-482a6c7889ec/5445ce6e-6273-47f0-84eb-621c86ca11cb/128"}}, "nickname": "hsu", "type": "user", "account_id": "557058:f3968cd3-4910-4384-8349-482a6c7889ec"}, "date": "2015-05-15T18:54:59.172323+00:00"}, "pull_request": {"type": "pullrequest", "id": 121, "links": {"self": {"href": "data/repositories/osrf/handsim/pullrequests/121.json"}, "html": {"href": "#!/osrf/handsim/pull-requests/121"}}, "title": "DRC Finals Demo: check a range of USB devices for tactors"}}, {"update": {"description": "The tactors were failing to activate because they look for device `/dev/ttyACM0` by default, but sometimes the USB devices shows up as `/dev/ttyACM1`. This pull request does a device sweep and returns with an error if none of the possible devices were found.", "title": "DRC Finals Demo: check a range of USB devices for tactors", "destination": {"commit": {"hash": "57edad95d0a7", "type": "commit", "links": {"self": {"href": "data/repositories/osrf/handsim/commit/57edad95d0a7.json"}, "html": {"href": "#!/osrf/handsim/commits/57edad95d0a7"}}}, "repository": {"links": {"self": {"href": "data/repositories/osrf/handsim.json"}, "html": {"href": "#!/osrf/handsim"}, "avatar": {"href": "data/bytebucket.org/ravatar/{9c7d89af-6eb6-40b1-9f69-da1ae9d129ce}ts=c_plus_plus"}}, "type": "repository", "name": "handsim", "full_name": "osrf/handsim", "uuid": "{9c7d89af-6eb6-40b1-9f69-da1ae9d129ce}"}, "branch": {"name": "game_demos"}}, "reason": "", "source": {"commit": {"hash": "0f2bdb772213", "type": "commit", "links": {"self": {"href": "data/repositories/osrf/handsim/commit/0f2bdb772213.json"}, "html": {"href": "#!/osrf/handsim/commits/0f2bdb772213"}}}, "repository": {"links": {"self": {"href": "data/repositories/osrf/handsim.json"}, "html": {"href": "#!/osrf/handsim"}, "avatar": {"href": "data/bytebucket.org/ravatar/{9c7d89af-6eb6-40b1-9f69-da1ae9d129ce}ts=c_plus_plus"}}, "type": "repository", "name": "handsim", "full_name": "osrf/handsim", "uuid": "{9c7d89af-6eb6-40b1-9f69-da1ae9d129ce}"}, "branch": {"name": "game_demos_tactors"}}, "state": "OPEN", "author": {"display_name": "Jackie K", "uuid": "{e3d60b62-b7c7-4863-b9b9-cdae9f123cec}", "links": {"self": {"href": "https://api.bitbucket.org/2.0/users/%7Be3d60b62-b7c7-4863-b9b9-cdae9f123cec%7D"}, "html": {"href": "https://bitbucket.org/%7Be3d60b62-b7c7-4863-b9b9-cdae9f123cec%7D/"}, "avatar": {"href": "data/secure.gravatar.com/avatar/ea011fa2919d4bd4568b32b440eda779d=httpsavatar-management--avatars.us-west-2.prod.public.atl-paas.netinitialsJK-0.png"}}, "nickname": "jacquelinekay", "type": "user", "account_id": "557058:f56c822f-f75c-4665-80f9-6e7764893b9c"}, "date": "2015-05-15T18:54:28.897169+00:00"}, "pull_request": {"type": "pullrequest", "id": 121, "links": {"self": {"href": "data/repositories/osrf/handsim/pullrequests/121.json"}, "html": {"href": "#!/osrf/handsim/pull-requests/121"}}, "title": "DRC Finals Demo: check a range of USB devices for tactors"}}, {"update": {"description": "The tactors were failing to activate because they look for device `/dev/ttyACM0` by default, but sometimes the USB devices shows up as `/dev/ttyACM1`. This pull request does a device sweep and returns with an error if none of the possible devices were found.", "title": "DRC Finals Demo: check a range of USB devices for tactors", "destination": {"commit": {"hash": "57edad95d0a7", "type": "commit", "links": {"self": {"href": "data/repositories/osrf/handsim/commit/57edad95d0a7.json"}, "html": {"href": "#!/osrf/handsim/commits/57edad95d0a7"}}}, "repository": {"links": {"self": {"href": "data/repositories/osrf/handsim.json"}, "html": {"href": "#!/osrf/handsim"}, "avatar": {"href": "data/bytebucket.org/ravatar/{9c7d89af-6eb6-40b1-9f69-da1ae9d129ce}ts=c_plus_plus"}}, "type": "repository", "name": "handsim", "full_name": "osrf/handsim", "uuid": "{9c7d89af-6eb6-40b1-9f69-da1ae9d129ce}"}, "branch": {"name": "game_demos"}}, "reason": "", "source": {"commit": {"hash": "0f2bdb772213", "type": "commit", "links": {"self": {"href": "data/repositories/osrf/handsim/commit/0f2bdb772213.json"}, "html": {"href": "#!/osrf/handsim/commits/0f2bdb772213"}}}, "repository": {"links": {"self": {"href": "data/repositories/osrf/handsim.json"}, "html": {"href": "#!/osrf/handsim"}, "avatar": {"href": "data/bytebucket.org/ravatar/{9c7d89af-6eb6-40b1-9f69-da1ae9d129ce}ts=c_plus_plus"}}, "type": "repository", "name": "handsim", "full_name": "osrf/handsim", "uuid": "{9c7d89af-6eb6-40b1-9f69-da1ae9d129ce}"}, "branch": {"name": "game_demos_tactors"}}, "state": "OPEN", "author": {"display_name": "Jackie K", "uuid": "{e3d60b62-b7c7-4863-b9b9-cdae9f123cec}", "links": {"self": {"href": "https://api.bitbucket.org/2.0/users/%7Be3d60b62-b7c7-4863-b9b9-cdae9f123cec%7D"}, "html": {"href": "https://bitbucket.org/%7Be3d60b62-b7c7-4863-b9b9-cdae9f123cec%7D/"}, "avatar": {"href": "data/secure.gravatar.com/avatar/ea011fa2919d4bd4568b32b440eda779d=httpsavatar-management--avatars.us-west-2.prod.public.atl-paas.netinitialsJK-0.png"}}, "nickname": "jacquelinekay", "type": "user", "account_id": "557058:f56c822f-f75c-4665-80f9-6e7764893b9c"}, "date": "2015-05-15T18:54:28.742109+00:00"}, "pull_request": {"type": "pullrequest", "id": 121, "links": {"self": {"href": "data/repositories/osrf/handsim/pullrequests/121.json"}, "html": {"href": "#!/osrf/handsim/pull-requests/121"}}, "title": "DRC Finals Demo: check a range of USB devices for tactors"}}]}