{"links": {"self": {"href": "data/repositories/osrf/handsim/pullrequests/3/comments/3663210.json"}, "html": {"href": "#!/osrf/handsim/pull-requests/3/_/diff#comment-3663210"}}, "parent": {"id": 3659896, "links": {"self": {"href": "data/repositories/osrf/handsim/pullrequests/3/comments/3659896.json"}, "html": {"href": "#!/osrf/handsim/pull-requests/3/_/diff#comment-3659896"}}}, "deleted": false, "pullrequest": {"type": "pullrequest", "id": 3, "links": {"self": {"href": "data/repositories/osrf/handsim/pullrequests/3.json"}, "html": {"href": "#!/osrf/handsim/pull-requests/3"}}, "title": "using actual motor and sensor sizes (previously haptix.h enums)"}, "content": {"raw": "currently\n~~~\ngazebo worlds/arat.world\n~~~\nand\n~~~\ngz model -f ./src/handsim_proprietary/apl_description/right_mpl_arm.urdf -m apl\n~~~\nsegfaults due to missing `polhemus_source` model. I'll fix HaptixControlPlugin to not segfault here.", "markup": "markdown", "html": "<p>currently</p>\n<div class=\"codehilite\"><pre><span></span>gazebo worlds/arat.world\n</pre></div>\n\n\n<p>and</p>\n<div class=\"codehilite\"><pre><span></span>gz model -f ./src/handsim_proprietary/apl_description/right_mpl_arm.urdf -m apl\n</pre></div>\n\n\n<p>segfaults due to missing <code>polhemus_source</code> model. I'll fix HaptixControlPlugin to not segfault here.</p>", "type": "rendered"}, "created_on": "2014-10-29T22:38:36.045724+00:00", "user": {"display_name": "John Hsu", "uuid": "{0a186eae-abf0-4514-a951-23db5eccc286}", "links": {"self": {"href": "https://api.bitbucket.org/2.0/users/%7B0a186eae-abf0-4514-a951-23db5eccc286%7D"}, "html": {"href": "https://bitbucket.org/%7B0a186eae-abf0-4514-a951-23db5eccc286%7D/"}, "avatar": {"href": "https://avatar-management--avatars.us-west-2.prod.public.atl-paas.net/557058:f3968cd3-4910-4384-8349-482a6c7889ec/5445ce6e-6273-47f0-84eb-621c86ca11cb/128"}}, "nickname": "hsu", "type": "user", "account_id": "557058:f3968cd3-4910-4384-8349-482a6c7889ec"}, "updated_on": "2014-10-29T22:38:36.056167+00:00", "type": "pullrequest_comment", "id": 3663210}