{"links": {"self": {"href": "data/repositories/osrf/haptix_api/pullrequests/2/comments/5048302.json"}, "html": {"href": "#!/osrf/haptix_api/pull-requests/2/_/diff#comment-5048302"}}, "deleted": false, "pullrequest": {"type": "pullrequest", "id": 2, "links": {"self": {"href": "data/repositories/osrf/haptix_api/pullrequests/2.json"}, "html": {"href": "#!/osrf/haptix_api/pull-requests/2"}}, "title": "Update C API"}, "content": {"raw": "Sorry to join today's party late... and I actually have to run to a class I am teaching. I will be back online later this evening.  A few brief comments:\n\n-- now that you are focusing on style and convention, I leave it in your capable hands and will adopt what you decide\n\n-- fine with me to put IMU orientation back.  what is your quaternion format?  mine is (w,x,y,z).  even if we are not providing data, we should at least send back a unit quaternion (1,0,0,0) instead of all zeros, because the latter is not a valid orientation quaternion\n\n-- based on the info we got from the MPL team today, ref_vel is not actuall ref_vel but rather ref_vel_max, i.e. the motor is computing its ref_vel internally from the positions, and using the user-supplied value to impose an upper bound.", "markup": "markdown", "html": "<p>Sorry to join today's party late... and I actually have to run to a class I am teaching. I will be back online later this evening.  A few brief comments:</p>\n<p>-- now that you are focusing on style and convention, I leave it in your capable hands and will adopt what you decide</p>\n<p>-- fine with me to put IMU orientation back.  what is your quaternion format?  mine is (w,x,y,z).  even if we are not providing data, we should at least send back a unit quaternion (1,0,0,0) instead of all zeros, because the latter is not a valid orientation quaternion</p>\n<p>-- based on the info we got from the MPL team today, ref_vel is not actuall ref_vel but rather ref_vel_max, i.e. the motor is computing its ref_vel internally from the positions, and using the user-supplied value to impose an upper bound.</p>", "type": "rendered"}, "created_on": "2015-02-09T23:31:53.573160+00:00", "user": {"display_name": "Emo Todorov", "uuid": "{c84af488-b11e-458d-9817-1aeafde381d2}", "links": {"self": {"href": "https://api.bitbucket.org/2.0/users/%7Bc84af488-b11e-458d-9817-1aeafde381d2%7D"}, "html": {"href": "https://bitbucket.org/%7Bc84af488-b11e-458d-9817-1aeafde381d2%7D/"}, "avatar": {"href": "https://bitbucket.org/account/emotodorov/avatar/"}}, "nickname": "emotodorov", "type": "user", "account_id": null}, "updated_on": "2015-02-09T23:34:28.638125+00:00", "type": "pullrequest_comment", "id": 5048302}