{"links": {"self": {"href": "data/repositories/osrf/haptix_api/pullrequests/2/comments/5066110.json"}, "html": {"href": "#!/osrf/haptix_api/pull-requests/2/_/diff#comment-5066110"}}, "parent": {"id": 5065745, "links": {"self": {"href": "data/repositories/osrf/haptix_api/pullrequests/2/comments/5065745.json"}, "html": {"href": "#!/osrf/haptix_api/pull-requests/2/_/diff#comment-5065745"}}}, "deleted": false, "pullrequest": {"type": "pullrequest", "id": 2, "links": {"self": {"href": "data/repositories/osrf/haptix_api/pullrequests/2.json"}, "html": {"href": "#!/osrf/haptix_api/pull-requests/2"}}, "title": "Update C API"}, "content": {"raw": "Didn't you say that ref_vel was changed to ref_vel_max?  It is not reflected in this version.  Otherwise everything looks good.", "markup": "markdown", "html": "<p>Didn't you say that ref_vel was changed to ref_vel_max?  It is not reflected in this version.  Otherwise everything looks good.</p>", "type": "rendered"}, "created_on": "2015-02-10T16:59:25.660701+00:00", "user": {"display_name": "Emo Todorov", "uuid": "{c84af488-b11e-458d-9817-1aeafde381d2}", "links": {"self": {"href": "https://api.bitbucket.org/2.0/users/%7Bc84af488-b11e-458d-9817-1aeafde381d2%7D"}, "html": {"href": "https://bitbucket.org/%7Bc84af488-b11e-458d-9817-1aeafde381d2%7D/"}, "avatar": {"href": "https://bitbucket.org/account/emotodorov/avatar/"}}, "nickname": "emotodorov", "type": "user", "account_id": null}, "updated_on": "2015-02-10T16:59:25.691371+00:00", "type": "pullrequest_comment", "id": 5066110}