{"links": {"self": {"href": "data/repositories/osrf/handsim/pullrequests/5/comments/3642874.json"}, "code": {"href": "https://api.bitbucket.org/2.0/repositories/osrf/handsim/diff/osrf/handsim:None..None?path=haptix_gazebo_plugins%2Fsrc%2FHaptixControlPlugin.cc"}, "html": {"href": "#!/osrf/handsim/pull-requests/5/_/diff#comment-3642874"}}, "parent": {"id": 3642778, "links": {"self": {"href": "data/repositories/osrf/handsim/pullrequests/5/comments/3642778.json"}, "html": {"href": "#!/osrf/handsim/pull-requests/5/_/diff#comment-3642778"}}}, "deleted": false, "pullrequest": {"type": "pullrequest", "id": 5, "links": {"self": {"href": "data/repositories/osrf/handsim/pullrequests/5.json"}, "html": {"href": "#!/osrf/handsim/pull-requests/5"}}, "title": "Cleaned up global variables in HaptixControlPlugin"}, "content": {"raw": "haha, sometimes I surprise myself with how inattentive I am to documentation...", "markup": "markdown", "html": "<p>haha, sometimes I surprise myself with how inattentive I am to documentation...</p>", "type": "rendered"}, "created_on": "2014-10-28T22:39:59.003935+00:00", "user": {"display_name": "Jackie K", "uuid": "{e3d60b62-b7c7-4863-b9b9-cdae9f123cec}", "links": {"self": {"href": "https://api.bitbucket.org/2.0/users/%7Be3d60b62-b7c7-4863-b9b9-cdae9f123cec%7D"}, "html": {"href": "https://bitbucket.org/%7Be3d60b62-b7c7-4863-b9b9-cdae9f123cec%7D/"}, "avatar": {"href": "data/secure.gravatar.com/avatar/ea011fa2919d4bd4568b32b440eda779d=httpsavatar-management--avatars.us-west-2.prod.public.atl-paas.netinitialsJK-0.png"}}, "nickname": "jacquelinekay", "type": "user", "account_id": "557058:f56c822f-f75c-4665-80f9-6e7764893b9c"}, "inline": {"to": null, "from": null, "outdated": false, "path": "haptix_gazebo_plugins/src/HaptixControlPlugin.cc"}, "updated_on": "2014-10-28T22:39:59.020619+00:00", "type": "pullrequest_comment", "id": 3642874}